Workbook

Sheet Dashboard
A1: Personal Finance Tracker
A3: Total Income | B3: Total Expenses | C3: Net Savings | D3: Savings Rate
A4: =SUMIF(Data!D:D,"Income",Data!E:E) -> 45000 | B4: =SUMIF(Data!D:D,"Expense",Data!E:E) -> 28970 | C4: =A4-B4 -> 16030 | D4: =IFERROR(ROUND(C4/A4*100,2),0) -> 35.62
A6: Category | B6: Budget | C6: Actual | D6: Difference
A7: Food | B7: =VLOOKUP(A7,Settings!A:B,2,0)*3 -> 4500 | C7: =SUMIFS(Data!E:E,Data!B:B,A7,Data!D:D,"Expense") -> 3700 | D7: =B7-C7 -> 800
A8: Transport | B8: =VLOOKUP(A8,Settings!A:B,2,0)*3 -> 1200 | C8: =SUMIFS(Data!E:E,Data!B:B,A8,Data!D:D,"Expense") -> 970 | D8: =B8-C8 -> 230
A9: Rent | B9: =VLOOKUP(A9,Settings!A:B,2,0)*3 -> 15000 | C9: =SUMIFS(Data!E:E,Data!B:B,A9,Data!D:D,"Expense") -> 15000 | D9: =B9-C9 -> 0
A10: Utilities | B10: =VLOOKUP(A10,Settings!A:B,2,0)*3 -> 1500 | C10: =SUMIFS(Data!E:E,Data!B:B,A10,Data!D:D,"Expense") -> 0 | D10: =B10-C10 -> 1500
A11: Phone Bill | B11: =VLOOKUP(A11,Settings!A:B,2,0)*3 -> 1500 | C11: =SUMIFS(Data!E:E,Data!B:B,A11,Data!D:D,"Expense") -> 1500 | D11: =B11-C11 -> 0
A12: Entertainment | B12: =VLOOKUP(A12,Settings!A:B,2,0)*3 -> 1800 | C12: =SUMIFS(Data!E:E,Data!B:B,A12,Data!D:D,"Expense") -> 1000 | D12: =B12-C12 -> 800
A13: Clothing | B13: =VLOOKUP(A13,Settings!A:B,2,0)*3 -> 2400 | C13: =SUMIFS(Data!E:E,Data!B:B,A13,Data!D:D,"Expense") -> 800 | D13: =B13-C13 -> 1600
A14: Savings | B14: =VLOOKUP(A14,Settings!A:B,2,0)*3 -> 6000 | C14: =SUMIFS(Data!E:E,Data!B:B,A14,Data!D:D,"Expense") -> 6000 | D14: =B14-C14 -> 0
A15: Other | B15: =VLOOKUP(A15,Settings!A:B,2,0)*3 -> 1500 | C15: =SUMIFS(Data!E:E,Data!B:B,A15,Data!D:D,"Expense") -> 0 | D15: =B15-C15 -> 1500
A16: Total | B16: =SUM(B7:B15) -> 35400 | C16: =SUM(C7:C15) -> 28970 | D16: =SUM(D7:D15) -> 6430

Sheet Data
A1: Date | B1: Category | C1: Description | D1: Type | E1: Amount
A2: 45658 | B2: Rent | C2: Monthly rent | D2: Expense | E2: 5000
A3: 45658 | B3: Food | C3: Groceries | D3: Expense | E3: 1200
A4: 45658 | B4: Transport | C4: Bus fare | D4: Expense | E4: 300
A5: 45658 | B5: Phone Bill | C5: Monthly bill | D5: Expense | E5: 500
A6: 45658 | B6: Savings | C6: Monthly savings | D6: Expense | E6: 2000
A7: 45658 | B7: Entertainment | C7: Cinema | D7: Expense | E7: 400
A8: 45672 | B8: Income | C8: Salary | D8: Income | E8: 15000
A9: 45689 | B9: Rent | C9: Monthly rent | D9: Expense | E9: 5000
A10: 45689 | B10: Food | C10: Groceries | D10: Expense | E10: 1400
A11: 45689 | B11: Transport | C11: Bus fare | D11: Expense | E11: 350
A12: 45689 | B12: Phone Bill | C12: Monthly bill | D12: Expense | E12: 500
A13: 45689 | B13: Savings | C13: Monthly savings | D13: Expense | E13: 2000
... A22: 45731 | B22: Income | C22: Salary | D22: Income | E22: 15000

Sheet Settings
A1: Category | B1: Monthly Budget
A2: Food | B2: 1500
A3: Transport | B3: 400
A4: Rent | B4: 5000
A5: Utilities | B5: 500
A6: Phone Bill | B6: 500
A7: Entertainment | B7: 600
A8: Clothing | B8: 800
A9: Savings | B9: 2000
A10: Other | B10: 500
